<BackupInst xmlns="http://www.microsoft.com/GroupPolicy/GPOOperations/Manifest"><GPOGuid><![CDATA[{1A250805-815C-4AE5-A786-E7178DEC51D3}]]></GPOGuid><GPODomain><![CDATA[HOME.LAN]]></GPODomain><GPODomainGuid><![CDATA[{eb839d55-4d66-49f3-9f82-b0d94bf8c9e8}]]></GPODomainGuid><GPODomainController><![CDATA[IRONMAN.HOME.LAN]]></GPODomainController><BackupTime><![CDATA[2022-04-06T23:35:10]]></BackupTime><ID><![CDATA[{E64A2C08-00E2-46EE-B0EC-4BE924588E7A}]]></ID><Comment><![CDATA[]]></Comment><GPODisplayName><![CDATA[Firewall Rules]]></GPODisplayName></BackupInst>
